playbacker/__init__.py
playbacker/app.py
playbacker/config.py
playbacker/core/__init__.py
playbacker/core/audiofile.py
playbacker/core/clock.py
playbacker/core/playback.py
playbacker/core/player.py
playbacker/core/setlist.py
playbacker/core/settings.py
playbacker/core/song.py
playbacker/core/stream.py
playbacker/core/tempo.py
playbacker/core/track.py
playbacker/core/tracks/__init__.py
playbacker/core/tracks/countdown.py
playbacker/core/tracks/metronome.py
playbacker/core/validate.py
playbacker/dist/assets/index-04f532a9.js
playbacker/dist/assets/index-c1f1d727.css
playbacker/dist/index.html
playbacker/main.py
playbacker-0.7.1.dist-info/METADATA
playbacker-0.7.1.dist-info/WHEEL
playbacker-0.7.1.dist-info/entry_points.txt
playbacker-0.7.1.dist-info/RECORD
